<?xml version="1.0" encoding="utf-8" ?>
<Upgrade OldVersion="2.1" NewVersion="2.2" xmlns:xsl="http://www.w3.org/1999/XSL/Transform">

  <Preprocessing>
  </Preprocessing>

  <Globals>

    <AddGlobal Description="Adding watermark text for global search" Name="GlobalSearchWatermarkText" Value="Search..." />
    <AddGlobal Description="Adding BiasResultsTowardsCenter for Instant Search" Name="BiasResultsTowardsCenter" Value="true" />

  </Globals>

  <UpdateModules>
    <!-- LayerList -->

    <AddElement Description="Adding 'Export to Shapefile' menu item to layer list"
                Path="/Configuration/Modules/LayerList/Views/View[@Id='LayerListView']/Configuration/Menus/Menu[@Id='LayerListSelectionActionsMenu']/Items/Item[@Command='ExportFeaturesToCsvWithExtras']"
                Name="Item"
                AddAfter="true">
      <Item Text="Export to Shapefile" Command="ExtractFeatureSet" />
    </AddElement>

    <!-- Results -->

    <AddElement Description="Adding 'Export to Shapefile' menu item to results list view"
                Path="/Configuration/Modules/Results/Configuration/Menus/Menu[@Id='ResultsListActions']/Items/Item[@Command='ShowChartingView']"
                Name="Item"
                AddAfter="true">
      <Item Text="Export to Shapefile" ToolTip="Export to Shapefile" Command="ExtractFeatureSetCollection" Module="Extract"/>
    </AddElement>

    <AddElement Description="Adding 'Export to Shapefile' menu item to results table view"
                Path="/Configuration/Modules/Results/Configuration/Menus/Menu[@Id='ResultsTableActions']/Items/Item[@Command='ExportFeaturesToCsvWithExtras']"
                Name="Item"
                AddAfter="true">
      <Item Text="Export to Shapefile" ToolTip="Export to Shapefile" Command="ExtractFeatureSet" Module="Extract"/>
    </AddElement>

    <!-- Selection -->

    <AddElement Description="Adding 'Export to Shapefile' menu item to selection actions"
                Path="/Configuration/Modules/Selection/Configuration/Menus/Menu[@Id='SelectionActions']/Items"
                Name="Item">
      <Item Text="Export to Shapefile" ToolTip="Export to Shapefile" Command="ExtractFeatureSetCollection"/>
    </AddElement>

    <AddElement Description="Adding 'Export to Shapefile' menu item to selection layer menu"
                Path="/Configuration/Modules/Selection/Configuration/Menus/Menu[@Id='SelectionLayerMenu']/Items/Item[@Command='ExportFeaturesToCsvWithExtras']"
                Name="Item"
                AddAfter="true">
      <Item Text="Export to Shapefile" Command="ExtractFeatureSet" />
    </AddElement>

    <AddElement Description="Adding 'Export to Shapefile' menu item to history actions"
                Path="/Configuration/Modules/Selection/Configuration/Menus/Menu[@Id='HistoricalResultsRootMenu']/Items/Item[@Command='RemoveCollection']"
                Name="Item"
                AddAfter="true">
      <Item Text="Export to Shapefile" ToolTip="Export to Shapefile" Command="ExtractFeatureSetCollection"/>
    </AddElement>

    <AddElement Description="Adding 'Export to Shapefile' menu item to history layer menu"
                Path="/Configuration/Modules/Selection/Configuration/Menus/Menu[@Id='HistoricalResultsLayerMenu']/Items/Item[@Command='ExportFeaturesToCsvWithExtras']"
                Name="Item"
                AddAfter="true">
      <Item Text="Export to Shapefile" Command="ExtractFeatureSet" />
    </AddElement>

    <AddAttribute Description="Adding global search watermark text to global search module" Path="/Configuration/Modules/GlobalSearch/Configuration" Name="Watermark" Value="{GlobalSearchWatermarkText}">
    </AddAttribute>
    <AddAttribute Description="Adding BiasResultsTowardsCenter to Instant Search module" Path="/Configuration/Modules/InstantSearch/Configuration" Name="BiasResultsTowardsCenter" Value="{BiasResultsTowardsCenter}" >
    </AddAttribute>

  </UpdateModules>

  <DeprecateModules>
  </DeprecateModules>

  <AddModules>
  </AddModules>

  <DocumentTransformations>

    <AddAttribute Description="Updating version attribute" ReplaceExisting="true" Path="/Configuration" Name="Version" Value="2.2" />

    <RegexTextReplace Description="Updating Uris to virtual directory content" Match="/Templates/SilverlightViewer_2_\d/VirtualDirectory/" ReplaceWith="/Templates/SilverlightViewer_2_2/VirtualDirectory/" />

  </DocumentTransformations>

</Upgrade>